{"crs": 4326, "type": "FeatureCollection", "features": [{"geometry": {"type": "Point", "coordinates": [-7.2917809999999967, 52.715344999999999]}, "type": "Feature", "id": 2334, "properties": {"url": "/0000015003/0002/", "csv_file": "/data/month/15003_0002.csv", "station.name": "Dinin Bridge", "value": 11.400, "datetime": "2018-05-15 13:00:00+00:00", "sensor.ref": "0002", "station.ref": "0000015003", "station.region_id": 9, "err_code": 99}}, {"geometry": {"type": "Point", "coordinates": [-9.0188539999999939, 52.462812999999976]}, "type": "Feature", "id": 280, "properties": {"url": "/0000024012/0001/", "csv_file": "/data/month/24012_0001.csv", "station.name": "Grange Bridge", "value": 0.612, "datetime": "2018-05-15 13:15:00+00:00", "sensor.ref": "0001", "station.ref": "0000024012", "station.region_id": 8, "err_code": 99}}, {"geometry": {"type": "Point", "coordinates": [-6.2214409884620574, 53.798040678733329]}, "type": "Feature", "id": 1609, "properties": {"url": "/0000006060/1300/", "csv_file": "/data/month/06060_1300.csv", "station.name": "Port Oriel", "value": 919.650, "datetime": "2013-01-02 04:20:00+00:00", "sensor.ref": "1300", "station.ref": "0000006060", "station.region_id": 10, "err_code": 99}}, {"geometry": {"type": "Point", "coordinates": [-7.9868602329863343, 53.467425373316097]}, "type": "Feature", "id": 1674, "properties": {"url": "/0000026088/1300/", "csv_file": "/data/month/26088_1300.csv", "station.name": "Hodson's Bay", "value": -41.640, "datetime": "2013-01-02 18:31:03+00:00", "sensor.ref": "1300", "station.ref": "0000026088", "station.region_id": 2, "err_code": 99}}, {"geometry": {"type": "Point", "coordinates": [-7.5034049999999928, 53.886690999999985]}, "type": "Feature", "id": 868, "properties": {"url": "/0000036012/0002/", "csv_file": "/data/month/36012_0002.csv", "station.name": "Sallaghan", "value": 0.000, "datetime": "2012-11-20 12:00:00+00:00", "sensor.ref": "0002", "station.ref": "0000036012", "station.region_id": 13, "err_code": 0}}, {"geometry": {"type": "Point", "coordinates": [-7.2917809999999967, 52.715344999999999]}, "type": "Feature", "id": 2335, "properties": {"url": "/0000015003/0003/", "csv_file": "/data/month/15003_0003.csv", "station.name": "Dinin Bridge", "value": 14.000, "datetime": "2018-05-15 13:00:00+00:00", "sensor.ref": "0003", "station.ref": "0000015003", "station.region_id": 9, "err_code": 99}}, {"geometry": {"type": "Point", "coordinates": [-9.321143999999995, 53.431399000000006]}, "type": "Feature", "id": 844, "properties": {"url": "/0000030101/OD/", "csv_file": "/data/month/30101_OD.csv", "station.name": "Oughterard", "value": 10.386, "datetime": "2018-05-15 13:15:00+00:00", "sensor.ref": "OD", "station.ref": "0000030101", "station.region_id": 11, "err_code": 99}}, {"geometry": {"type": "Point", "coordinates": [-8.9307709999999965, 53.967499999999987]}, "type": "Feature", "id": 592, "properties": {"url": "/0000034010/OD/", "csv_file": "/data/month/34010_OD.csv", "station.name": "Cloonacannana", "value": 39.634, "datetime": "2018-05-15 13:15:00+00:00", "sensor.ref": "OD", "station.ref": "0000034010", "station.region_id": 3, "err_code": 99}}, {"geometry": {"type": "Point", "coordinates": [-6.2214409884620574, 53.798040678733329]}, "type": "Feature", "id": 2518, "properties": {"url": "/0000006060/OD/", "csv_file": "/data/month/06060_OD.csv", "station.name": "Port Oriel", "value": 0.716, "datetime": "2018-05-15 13:15:00+00:00", "sensor.ref": "OD", "station.ref": "0000006060", "station.region_id": 10, "err_code": 99}}, {"geometry": {"type": "Point", "coordinates": [-6.3854687985318357, 54.00768862093954]}, "type": "Feature", "id": 2521, "properties": {"url": "/0000006061/OD/", "csv_file": "/data/month/06061_OD.csv", "station.name": "Dundalk Port", "value": 1.038, "datetime": "2018-05-15 13:15:00+00:00", "sensor.ref": "OD", "station.ref": "0000006061", "station.region_id": 10, "err_code": 99}}, {"geometry": {"type": "Point", "coordinates": [-9.2080760000000108, 53.977664999999988]}, "type": "Feature", "id": 808, "properties": {"url": "/0000034081/0001/", "csv_file": "/data/mon